{
  "vocab_size": 53,
  "num_training_names": 1000,
  "hyperparameters": {
    "embed_dim": 64,
    "hidden_size": 256,
    "num_layers": 2,
    "dropout": 0.3,
    "attention_dim": 128,
    "learning_rate": 0.002,
    "batch_size": 64
  },
  "model_params": {
    "Vanilla RNN": 230517,
    "BLSTM": 3372149,
    "RNN + Attention": 856053
  },
  "final_losses": {
    "Vanilla RNN": 1.722952239215374,
    "BLSTM": 1.4419923424720764,
    "RNN + Attention": 1.4033565819263458
  },
  "evaluation": {
    "Vanilla RNN": {
      "novelty_rate": 63.4,
      "diversity": 87.8,
      "unique_count": 439,
      "avg_length": 7.838
    },
    "BLSTM": {
      "novelty_rate": 48.0,
      "diversity": 88.8,
      "unique_count": 444,
      "avg_length": 8.448
    },
    "RNN + Attention": {
      "novelty_rate": 43.8,
      "diversity": 84.39999999999999,
      "unique_count": 422,
      "avg_length": 8.392
    }
  },
  "sample_names": {
    "Vanilla RNN": [
      "Malini",
      "Zara",
      "Aman",
      "Harishram",
      "Soumyadip",
      "Ayush",
      "Raj",
      "Souudas",
      "Sugany",
      "Rajeshwaridevo",
      "Divyadev",
      "Latiwashram",
      "Naveon",
      "Vennilam",
      "Saurabh",
      "Prasekhar",
      "Bhavyek",
      "Tarun",
      "Harijaykram",
      "Naimusham",
      "Sangektchana",
      "Padminidevi",
      "Pavithrani",
      "Aparno",
      "Swatiram",
      "Narmogam",
      "Susmita",
      "Balwinder",
      "Siwarupal",
      "Narmidha"
    ],
    "BLSTM": [
      "Ravikumar",
      "Priyanshi",
      "Gitaporvi",
      "Lubnaprabhe",
      "Raghsanakumar",
      "Kamyal",
      "Maohurimawjz",
      "Amanprevt",
      "Ramya",
      "Vaibhav",
      "Prathapdevi",
      "Sharmistha",
      "Subhashrez",
      "Gurdehprabhu",
      "Karvinder",
      "Nadem",
      "Tanyalaj",
      "Avni",
      "Suganygalelal",
      "Madhuram",
      "Prateek",
      "Zoya",
      "Antarj",
      "Ramya",
      "Amjit",
      "Gurjeet",
      "Pujarani",
      "Jagjeltrani",
      "Devarniv",
      "Tara"
    ],
    "RNN + Attention": [
      "Prachi",
      "Gitamohsin",
      "Karhil",
      "Sidwarup",
      "Srilakshmi",
      "Malintamhari",
      "Harijayalritya",
      "Sekhil",
      "Gitapotai",
      "Subhajit",
      "Devesh",
      "Lekha",
      "Sangeeta",
      "Abhisdek",
      "Sahil",
      "Tariqprabha",
      "Sabyasyuchi",
      "Mythilszi",
      "Harizafqrasr",
      "Amwit",
      "Amritpilatla",
      "Abhay",
      "Shanmugam",
      "Harioviya",
      "Jayitamalfa",
      "Yith",
      "Anaghva",
      "Latgcenuka",
      "Jagjeetkumar",
      "Scharapvdwa"
    ]
  }
}